Metadata-Version: 2.1
Name: oursms-py
Version: 0.9
Summary: a oursms Library in python
Home-page: https://notabug.org/alimiracle/oursms_py
Author: alimiracle
Author-email: alimiracle@riseup.net
License: UNKNOWN
Platform: UNKNOWN
Classifier: Programming Language :: Python
Classifier: License :: OSI Approved :: GNU Affero General Public License v3
Classifier: Operating System :: OS Independent
